Workbook

Sheet Inputs
A1: Input | B1: Value
A2: Revenue (EUR m) | B2: 1200
A3: EBITDA | B3: 120
A4: Interest expense | B4: 22
A5: Tax paid | B5: 18
A6: Total debt | B6: 480
A7: Group rating | B7: A-
A8: Max implicit-support notches | B8: 2
A9: Currency | B9: EUR
A10: Tenor (years) | B10: 5
A11: Principal (EUR m) | B11: 50
A12: Secured (1/0) | B12: 0
A13: Subordinated (1/0) | B13: 0

Sheet Scorecard
A1: Factor | B1: Ratio | C1: Weight | D1: Higher is better | E1: Score | F1: Weighted | G1: AAA | H1: AA | I1: A | J1: BBB | K1: BB | L1: B | M1: CCC
A2: EBITDA margin | B2: =Inputs!$B$3/Inputs!$B$2 -> 0.1 | C2: 0.15 | D2: 1 | E2: =IF($D$2=1,IF($B$2>=$G$2,1,IF($B$2<=$M$2,7,MATCH($B$2,$G$2:$M$2,-1)+(INDEX($G$2:$M$2,MATCH($B$2,$G$2:$M$2,-1))-$B$2)/(INDEX($G$2:$M$2,MATCH($B$2,$G$2:$M$2,-1))-INDEX($G$2:$M$2,MATCH($B$2,$G$2:$M$2,-1)+1)))),IF($B$2<=$G$2,1,IF($B$2>=$M$2,7,MATCH($B$2,$G$2:$M$2,1)+($B$2-INDEX($G$2:$M$2,MATCH($B$2,$G$2:$M$2,1)))/(INDEX($G$2:$M$2,MATCH($B$2,$G$2:$M$2,1)+1)-INDEX($G$2:$M$2,MATCH($B$2,$G$2:$M$2,1)))))) -> 5.2 | F2: =$C$2*$E$2 -> 0.78 | G2: 0.35 | H2: 0.28 | I2: 0.22 | J2: 0.16 | K2: 0.11 | L2: 0.06 | M2: 0.02
A3: Debt / EBITDA | B3: =Inputs!$B$6/Inputs!$B$3 -> 4 | C3: 0.25 | D3: 0 | E3: =IF($D$3=1,IF($B$3>=$G$3,1,IF($B$3<=$M$3,7,MATCH($B$3,$G$3:$M$3,-1)+(INDEX($G$3:$M$3,MATCH($B$3,$G$3:$M$3,-1))-$B$3)/(INDEX($G$3:$M$3,MATCH($B$3,$G$3:$M$3,-1))-INDEX($G$3:$M$3,MATCH($B$3,$G$3:$M$3,-1)+1)))),IF($B$3<=$G$3,1,IF($B$3>=$M$3,7,MATCH($B$3,$G$3:$M$3,1)+($B$3-INDEX($G$3:$M$3,MATCH($B$3,$G$3:$M$3,1)))/(INDEX($G$3:$M$3,MATCH($B$3,$G$3:$M$3,1)+1)-INDEX($G$3:$M$3,MATCH($B$3,$G$3:$M$3,1)))))) -> 5 | F3: =$C$3*$E$3 -> 1.25 | G3: 0.5 | H3: 1 | I3: 1.75 | J3: 2.75 | K3: 4 | L3: 5.5 | M3: 7.5
A4: EBITDA / interest | B4: =Inputs!$B$3/Inputs!$B$4 -> 5.4545455 | C4: 0.25 | D4: 1 | E4: =IF($D$4=1,IF($B$4>=$G$4,1,IF($B$4<=$M$4,7,MATCH($B$4,$G$4:$M$4,-1)+(INDEX($G$4:$M$4,MATCH($B$4,$G$4:$M$4,-1))-$B$4)/(INDEX($G$4:$M$4,MATCH($B$4,$G$4:$M$4,-1))-INDEX($G$4:$M$4,MATCH($B$4,$G$4:$M$4,-1)+1)))),IF($B$4<=$G$4,1,IF($B$4>=$M$4,7,MATCH($B$4,$G$4:$M$4,1)+($B$4-INDEX($G$4:$M$4,MATCH($B$4,$G$4:$M$4,1)))/(INDEX($G$4:$M$4,MATCH($B$4,$G$4:$M$4,1)+1)-INDEX($G$4:$M$4,MATCH($B$4,$G$4:$M$4,1)))))) -> 3.8863636 | F4: =$C$4*$E$4 -> 0.97159091 | G4: 25 | H4: 15 | I4: 9 | J4: 5 | K4: 3 | L4: 1.5 | M4: 0.75
A5: FFO / debt | B5: =(Inputs!$B$3-Inputs!$B$4-Inputs!$B$5)/Inputs!$B$6 -> 0.16666667 | C5: 0.2 | D5: 1 | E5: =IF($D$5=1,IF($B$5>=$G$5,1,IF($B$5<=$M$5,7,MATCH($B$5,$G$5:$M$5,-1)+(INDEX($G$5:$M$5,MATCH($B$5,$G$5:$M$5,-1))-$B$5)/(INDEX($G$5:$M$5,MATCH($B$5,$G$5:$M$5,-1))-INDEX($G$5:$M$5,MATCH($B$5,$G$5:$M$5,-1)+1)))),IF($B$5<=$G$5,1,IF($B$5>=$M$5,7,MATCH($B$5,$G$5:$M$5,1)+($B$5-INDEX($G$5:$M$5,MATCH($B$5,$G$5:$M$5,1)))/(INDEX($G$5:$M$5,MATCH($B$5,$G$5:$M$5,1)+1)-INDEX($G$5:$M$5,MATCH($B$5,$G$5:$M$5,1)))))) -> 4.5333333 | F5: =$C$5*$E$5 -> 0.90666667 | G5: 0.8 | H5: 0.55 | I5: 0.35 | J5: 0.22 | K5: 0.12 | L5: 0.06 | M5: 0.02
A6: Revenue (EUR m) | B6: =Inputs!$B$2 -> 1200 | C6: 0.15 | D6: 1 | E6: =IF($D$6=1,IF($B$6>=$G$6,1,IF($B$6<=$M$6,7,MATCH($B$6,$G$6:$M$6,-1)+(INDEX($G$6:$M$6,MATCH($B$6,$G$6:$M$6,-1))-$B$6)/(INDEX($G$6:$M$6,MATCH($B$6,$G$6:$M$6,-1))-INDEX($G$6:$M$6,MATCH($B$6,$G$6:$M$6,-1)+1)))),IF($B$6<=$G$6,1,IF($B$6>=$M$6,7,MATCH($B$6,$G$6:$M$6,1)+($B$6-INDEX($G$6:$M$6,MATCH($B$6,$G$6:$M$6,1)))/(INDEX($G$6:$M$6,MATCH($B$6,$G$6:$M$6,1)+1)-INDEX($G$6:$M$6,MATCH($B$6,$G$6:$M$6,1)))))) -> 4.7647059 | F6: =$C$6*$E$6 -> 0.71470588 | G6: 50000 | H6: 20000 | I6: 7500 | J6: 2500 | K6: 800 | L6: 250 | M6: 75
A8: Weighted score | F8: =SUM(F2:F6) -> 4.6229635
A9: Stand-alone rating | F9: =INDEX(Notches!$A$1:$A$21,MIN(21,MAX(1,3+ROUND((F8-2)*3,0)))) -> BB+
A10: Implicit-support lift (notches) | F10: =MIN(MAX(MATCH(F9,Notches!$A$1:$A$21,0)-MATCH(Inputs!$B$7,Notches!$A$1:$A$21,0),0),Inputs!$B$8) -> 2
A11: Supported rating | F11: =INDEX(Notches!$A$1:$A$21,MATCH(F9,Notches!$A$1:$A$21,0)-F10) -> BBB

Sheet Notches
A1: AAA
A2: AA+
A3: AA
A4: AA-
A5: A+
A6: A
A7: A-
A8: BBB+
A9: BBB
A10: BBB-
A11: BB+
A12: BB
... A21: C

Sheet Spreads
A1: Rating \ tenor | B1: 1 | C1: 2 | D1: 3 | E1: 5 | F1: 7 | G1: 10
A2: AAA | B2: 24.1 | C2: 29.2 | D2: 35.6 | E2: 45.8 | F2: 57.2 | G2: 68.7
A3: AA+ | B3: 29 | C3: 34.2 | D3: 42.2 | E3: 52.4 | F3: 65.5 | G3: 78.6
A4: AA | B4: 35 | C4: 40 | D4: 50 | E4: 60 | F4: 75 | G4: 90
A5: AA- | B5: 40.7 | C5: 47 | D5: 58.5 | E5: 71.1 | F5: 87.7 | G5: 104.3
A6: A+ | B6: 47.3 | C6: 55.3 | D6: 68.4 | E6: 84.3 | F6: 102.6 | G6: 120.8
A7: A | B7: 55 | C7: 65 | D7: 80 | E7: 100 | F7: 120 | G7: 140
A8: A- | B8: 64.8 | C8: 77.5 | D8: 95.2 | E8: 119.3 | F8: 142.3 | G8: 165.2
A9: BBB+ | B9: 76.4 | C9: 92.3 | D9: 113.4 | E9: 142.4 | F9: 168.7 | G9: 194.9
A10: BBB | B10: 90 | C10: 110 | D10: 135 | E10: 170 | F10: 200 | G10: 230
A11: BBB- | B11: 113.4 | C11: 138.6 | D11: 170.1 | E11: 212.1 | F11: 247.7 | G11: 283.3
A12: BB+ | B12: 142.9 | C12: 174.6 | D12: 214.3 | E12: 264.5 | F12: 306.8 | G12: 349.1
... A18: CCC+ | B18: 486.6 | C18: 571 | D18: 660.4 | E18: 786.9 | F18: 908.6 | G18: 1030.3

Sheet BaseRates
A1: Currency \ tenor | B1: 1 | C1: 2 | D1: 3 | E1: 5 | F1: 7 | G1: 10
A2: EUR | B2: 0.023 | C2: 0.0235 | D2: 0.024 | E2: 0.0255 | F2: 0.027 | G2: 0.029
A3: USD | B3: 0.041 | C3: 0.0395 | D3: 0.039 | E3: 0.0395 | F3: 0.0405 | G3: 0.042

Sheet Pricing
A1: Item | B1: Value
A2: Supported rating | B2: =Scorecard!$F$11 -> BBB
A3: Base rate | B3: =IF(Inputs!$B$10>=INDEX(Spreads!$B$1:$G$1,1,6),INDEX(BaseRates!$B$2:$G$3,MATCH(Inputs!$B$9,BaseRates!$A$2:$A$3,0),6),IF(Inputs!$B$10=INDEX(Spreads!$B$1:$G$1,1,MATCH(Inputs!$B$10,Spreads!$B$1:$G$1,1)),INDEX(BaseRates!$B$2:$G$3,MATCH(Inputs!$B$9,BaseRates!$A$2:$A$3,0),MATCH(Inputs!$B$10,Spreads!$B$1:$G$1,1)),INDEX(BaseRates!$B$2:$G$3,MATCH(Inputs!$B$9,BaseRates!$A$2:$A$3,0),MATCH(Inputs!$B$10,Spreads!$B$1:$G$1,1))+(LN(Inputs!$B$10)-LN(INDEX(Spreads!$B$1:$G$1,1,MATCH(Inputs!$B$10,Spreads!$B$1:$G$1,1))))/(LN(INDEX(Spreads!$B$1:$G$1,1,MATCH(Inputs!$B$10,Spreads!$B$1:$G$1,1)+1))-LN(INDEX(Spreads!$B$1:$G$1,1,MATCH(Inputs!$B$10,Spreads!$B$1:$G$1,1))))*(INDEX(BaseRates!$B$2:$G$3,MATCH(Inputs!$B$9,BaseRates!$A$2:$A$3,0),MATCH(Inputs!$B$10,Spreads!$B$1:$G$1,1)+1)-INDEX(BaseRates!$B$2:$G$3,MATCH(Inputs!$B$9,BaseRates!$A$2:$A$3,0),MATCH(Inputs!$B$10,Spreads!$B$1:$G$1,1))))) -> 0.0255
A4: Credit spread (bps) | B4: =IF(Inputs!$B$10>=INDEX(Spreads!$B$1:$G$1,1,6),INDEX(Spreads!$B$2:$G$18,MATCH(Scorecard!$F$11,Spreads!$A$2:$A$18,0),6),IF(Inputs!$B$10=INDEX(Spreads!$B$1:$G$1,1,MATCH(Inputs!$B$10,Spreads!$B$1:$G$1,1)),INDEX(Spreads!$B$2:$G$18,MATCH(Scorecard!$F$11,Spreads!$A$2:$A$18,0),MATCH(Inputs!$B$10,Spreads!$B$1:$G$1,1)),EXP(LN(INDEX(Spreads!$B$2:$G$18,MATCH(Scorecard!$F$11,Spreads!$A$2:$A$18,0),MATCH(Inputs!$B$10,Spreads!$B$1:$G$1,1)))+(LN(Inputs!$B$10)-LN(INDEX(Spreads!$B$1:$G$1,1,MATCH(Inputs!$B$10,Spreads!$B$1:$G$1,1))))/(LN(INDEX(Spreads!$B$1:$G$1,1,MATCH(Inputs!$B$10,Spreads!$B$1:$G$1,1)+1))-LN(INDEX(Spreads!$B$1:$G$1,1,MATCH(Inputs!$B$10,Spreads!$B$1:$G$1,1))))*(LN(INDEX(Spreads!$B$2:$G$18,MATCH(Scorecard!$F$11,Spreads!$A$2:$A$18,0),MATCH(Inputs!$B$10,Spreads!$B$1:$G$1,1)+1))-LN(INDEX(Spreads!$B$2:$G$18,MATCH(Scorecard!$F$11,Spreads!$A$2:$A$18,0),MATCH(Inputs!$B$10,Spreads!$B$1:$G$1,1))))))) -> 170
A5: Security / subordination adj. (bps) | B5: =Inputs!$B$12*(-25)+Inputs!$B$13*(75) -> 0
A6: All-in interest rate | B6: =B3+(B4+B5)/10000 -> 0.0425
A7: Annual interest (EUR m) | B7: =B6*Inputs!$B$11 -> 2.125
